invitetools/__init__.py
invitetools/invitetools.py
invitetools-0.1.1.dist-info/LICENSE
invitetools-0.1.1.dist-info/METADATA
invitetools-0.1.1.dist-info/WHEEL
invitetools-0.1.1.dist-info/top_level.txt
invitetools-0.1.1.dist-info/RECORD
